wsl2gpg/__init__.py
wsl2gpg-0.0.2.dist-info/LICENSE
wsl2gpg-0.0.2.dist-info/METADATA
wsl2gpg-0.0.2.dist-info/WHEEL
wsl2gpg-0.0.2.dist-info/entry_points.txt
wsl2gpg-0.0.2.dist-info/top_level.txt
wsl2gpg-0.0.2.dist-info/RECORD
