Metadata-Version: 2.1
Name: wsl2gpg
Version: 0.0.2
Summary: Create UNIX sockets and proxy to the gpg4win agent
Home-page: https://github.com/mensi/wsl2gpg
Author: Manuel Stocker
Author-email: mensi@mensi.ch
License: UNKNOWN
Platform: UNKNOWN
Classifier: Programming Language :: Python :: 3
Classifier: License :: OSI Approved :: Apache Software License
Classifier: Operating System :: POSIX
Requires-Python: >=3.5
